cloud_auto_deployor/__init__.py
cloud_auto_deployor/aci_deployer.py
cloud_auto_deployor/acr_handler.py
cloud_auto_deployor/builder.py
cloud_auto_deployor/config.json
cloud_auto_deployor/logger.py
cloud_auto_deployor/main.py
cloud_auto_deployor-1.0.6.dist-info/LICENSE
cloud_auto_deployor-1.0.6.dist-info/METADATA
cloud_auto_deployor-1.0.6.dist-info/WHEEL
cloud_auto_deployor-1.0.6.dist-info/entry_points.txt
cloud_auto_deployor-1.0.6.dist-info/top_level.txt
cloud_auto_deployor-1.0.6.dist-info/RECORD
