Metadata-Version: 2.1
Name: cloud_auto_deployor
Version: 1.0.6
Summary: A Python CLI library for automated cloud deployment to Azure (ACI + ACR)
Home-page: https://github.com/Raja900-del/cloud_auto_deployor
Author: Raja P
Author-email: your_email@example.com
Classifier: Programming Language :: Python :: 3
Classifier: License :: OSI Approved :: MIT License
Classifier: Operating System :: OS Independent
Requires-Python: >=3.9
License-File: LICENSE
Requires-Dist: azure-cli
Requires-Dist: docker
Requires-Dist: pyyaml
